siman/3d_plot.py
siman/SSHTools.py
siman/__init__.py
siman/analysis.py
siman/bands.py
siman/calc_manage.py
siman/calcul.py
siman/classes.py
siman/database.py
siman/default_project_conf.py
siman/dos_functions.py
siman/fit_hex.py
siman/functions.py
siman/geo.py
siman/header.py
siman/helper_for_writing_beatiful_code.py
siman/impurity.py
siman/inout.py
siman/matproj_functions.py
siman/monte.py
siman/monte_functions.py
siman/neb.py
siman/pairs.py
siman/picture_functions.py
siman/polaron.py
siman/polaron_hop.py
siman/project_funcs.py
siman/set_functions.py
siman/simanrc.py
siman/small_classes.py
siman/small_functions.py
siman/table_functions.py
siman/thermo.py
siman/workflow_utilities.py
siman/chg/__init__.py
siman/chg/chg_func.py
siman/chg/vasputil_chgarith_module.py
siman-1.0.2.dist-info/DESCRIPTION.rst
siman-1.0.2.dist-info/METADATA
siman-1.0.2.dist-info/RECORD
siman-1.0.2.dist-info/WHEEL
siman-1.0.2.dist-info/metadata.json
siman-1.0.2.dist-info/top_level.txt
