Metadata-Version: 2.0
Name: siman
Version: 1.0.2
Summary: Manager for DFT calculations
Home-page: https://github.com/dimonaks/siman
Author: Dmitry Aksenov
Author-email: dimonaks@gmail.com
License: GPL
Keywords: DFT VASP Density Functional Theory NEB DFT+U PAW GGA Monte-Carlo
Platform: UNKNOWN
Classifier: Programming Language :: Python :: 3
Classifier: License :: OSI Approved :: GNU General Public License (GPL)
Classifier: Operating System :: OS Independent
Requires-Dist: numpy
Requires-Dist: tabulate
Requires-Dist: pymatgen
Requires-Dist: pandas
Requires-Dist: scipy
Requires-Dist: six
Requires-Dist: matplotlib
Requires-Dist: ase
Requires-Dist: paramiko
Requires-Dist: adjustText
